psprocsdict/README.MD
psprocsdict/__init__.py
psprocsdict/requirements.txt
psprocsdict/thirdparty.json
psprocsdict-0.10.dist-info/LICENSE.rst
psprocsdict-0.10.dist-info/METADATA
psprocsdict-0.10.dist-info/WHEEL
psprocsdict-0.10.dist-info/top_level.txt
psprocsdict-0.10.dist-info/RECORD
