Metadata-Version: 2.1
Name: psprocsdict
Version: 0.10
Summary: powershell/wmic to dict
Home-page: https://github.com/hansalemaos/psprocsdict
Author: Johannes Fischer
Author-email: aulasparticularesdealemaosp@gmail.com
License: MIT
Keywords: powershell,wmic
Classifier: Development Status :: 4 - Beta
Classifier: Programming Language :: Python :: 3 :: Only
Classifier: Programming Language :: Python :: 3.10
Classifier: Topic :: Software Development :: Libraries :: Python Modules
Classifier: Topic :: Utilities
License-File: LICENSE.rst
Requires-Dist: numpy
Requires-Dist: numpyslicesplit
Requires-Dist: numpytypechecker
